fusion_solar_py/__init__.py
fusion_solar_py/captcha_solver_onnx.py
fusion_solar_py/client.py
fusion_solar_py/constants.py
fusion_solar_py/ctc_decoder.py
fusion_solar_py/encryption.py
fusion_solar_py/exceptions.py
fusion_solar_py/interfaces.py
fusion_solar_py-0.0.28.dist-info/licenses/LICENSE.txt
fusion_solar_py-0.0.28.dist-info/METADATA
fusion_solar_py-0.0.28.dist-info/WHEEL
fusion_solar_py-0.0.28.dist-info/top_level.txt
fusion_solar_py-0.0.28.dist-info/RECORD
