Metadata-Version: 2.4
Name: fusion_solar_py
Version: 0.0.28
Summary: A simply API to the Huawei Fusion Solar web interface.
Home-page: https://github.com/jgriss/FusionSolarPy
Author: Johannes Griss
Author-email: johannes.griss@meduniwien.ac.at
Project-URL: Bug Tracker, https://github.com/jgriss/FusionSolarPy/issues
Classifier: Programming Language :: Python :: 3
Classifier: License :: OSI Approved :: MIT License
Classifier: Operating System :: OS Independent
Requires-Python: >=3.9
License-File: LICENSE.txt
Requires-Dist: requests>=2.31.0
Requires-Dist: cryptography
Provides-Extra: captcha
Requires-Dist: beautifulsoup4>=4.12.2; extra == "captcha"
Requires-Dist: numpy<2.0.0; extra == "captcha"
Requires-Dist: opencv_python>=4.8.0.76; extra == "captcha"
Requires-Dist: onnxruntime>=1.14; extra == "captcha"
Dynamic: license-file
